flsr/__main__.py
flsr/lib_search.py
flsr-0.1.1.dist-info/METADATA
flsr-0.1.1.dist-info/WHEEL
flsr-0.1.1.dist-info/entry_points.txt
flsr-0.1.1.dist-info/RECORD
