Metadata-Version: 2.1
Name: flsr
Version: 0.1.1
Summary: 
Author: Denis Kustov
Author-email: you@example.com
Requires-Python: >=3.11,<4.0
Classifier: Programming Language :: Python :: 3
Classifier: Programming Language :: Python :: 3.11
Requires-Dist: tqdm (>=4.65.0,<5.0.0)
